{
  "project_info": {
    "project_number": "130100718968",
    "project_id": "mithackathon"
  },
  "client": [
    {
      "client_info": {
        "mobilesdk_app_id": "1:130100718968:android:a7fee36547527cba",
        "android_client_info": {
          "package_name": "crazy.hackathon.com.medheart"
        }
      },
      "oauth_client": [],
      "api_key": [
        {
          "current_key": "AIzaSyBCl1n4QObrMtkLm7chk1mbBxJHotdaDvA"
        }
      ],
      "services": {
        "analytics_service": {
          "status": 2,
          "analytics_property": {
            "tracking_id": "UA-69659403-2"
          }
        },
        "appinvite_service": {
          "status": 1,
          "other_platform_oauth_client": []
        },
        "ads_service": {
          "status": 1
        }
      }
    }
  ],
  "configuration_version": "1"
}